{
  "name": "clubs/R0a8BjOvIB8i5MP6THj8/burgee.png",
  "bucket": "club-trophies.appspot.com",
  "metageneration": 1,
  "generation": 1674149718575,
  "contentType": "image/png",
  "storageClass": "STANDARD",
  "contentDisposition": "inline",
  "downloadTokens": [
    "af24fce9-a2a3-4810-8a5d-063aaff6e06f"
  ],
  "etag": "p3wnVXOnsmpZUfNCASUppiWthvg",
  "customMetadata": {},
  "timeCreated": "2023-01-19T17:35:18.575Z",
  "updated": "2023-01-19T17:35:18.575Z",
  "size": 6601,
  "md5Hash": "D9dzeHrEun5IjXWRvaUu/A==",
  "crc32c": "397440039"
}