{
  "name": "clubs/R0a8BjOvIB8i5MP6THj8/trophies/xdaFeIRP54EGFNPFreK9/files/Da9czA997ayp13Edvl0Y-th.jpg",
  "bucket": "club-trophies.appspot.com",
  "metageneration": 2,
  "generation": 1673965435014,
  "contentType": "image/jpeg",
  "storageClass": "STANDARD",
  "contentDisposition": "inline",
  "downloadTokens": [
    "a3cc4d36-f378-458a-b19d-229416bff29a"
  ],
  "etag": "7HLur3+31ViBCN977qW61/4xUrc",
  "timeCreated": "2023-01-17T14:23:55.014Z",
  "updated": "2023-01-17T14:24:00.361Z",
  "size": 10905,
  "md5Hash": "uh30ULMbtTATGQ3fIMaiaQ==",
  "crc32c": "1081179431"
}